clube_betionario/__init__.py
clube_betionario-3.5.1.dist-info/LICENSE
clube_betionario-3.5.1.dist-info/METADATA
clube_betionario-3.5.1.dist-info/WHEEL
clube_betionario-3.5.1.dist-info/top_level.txt
clube_betionario-3.5.1.dist-info/RECORD
