Metadata-Version: 2.1
Name: clube-betionario
Version: 3.5.1
Summary: Clube Betionário. Aprenda Investimento em Futebol Passo a Passo Rápido. Melhor Preço até 00h00 de Hoje. Últimas Vagas. Só abrirá em 2022 de novo!
Home-page: https://github.com/pypa/sampleproject
Author: Emilly Oliveira
Author-email: author@example.com
License: UNKNOWN
Project-URL: Bug Tracker, https://github.com/pypa/sampleproject/issues
Platform: UNKNOWN
Classifier: Programming Language :: Python :: 3
Classifier: License :: OSI Approved :: MIT License
Classifier: Operating System :: OS Independent
Requires-Python: >=3.6
